ankigengpt/__init__.py
ankigengpt/__main__.py
ankigengpt/anki.py
ankigengpt/cli.py
ankigengpt/epub.py
ankigengpt/gpt.py
ankigengpt/kindle.py
ankigengpt/kobo.py
ankigengpt/logging.py
ankigengpt/misc.py
ankigengpt/models.py
ankigengpt/templates/__init__.py
ankigengpt/templates/epub.j2
ankigengpt/templates/introduction.j2
ankigengpt/templates/kindle.j2
ankigengpt/templates/plain.j2
ankigengpt-1.3.0.dist-info/METADATA
ankigengpt-1.3.0.dist-info/WHEEL
ankigengpt-1.3.0.dist-info/entry_points.txt
ankigengpt-1.3.0.dist-info/RECORD
